README
mogilelocal.py
setup.py
MogileLocal.egg-info/PKG-INFO
MogileLocal.egg-info/SOURCES.txt
MogileLocal.egg-info/dependency_links.txt
MogileLocal.egg-info/top_level.txt
MogileLocal.egg-info/zip-safe