Metadata-Version: 1.0
Name: MogileLocal
Version: 0.9.0
Summary: MogileFS client that uses the local filesystem as backing storage
Home-page: http://jonathan.tang.name/code/mogilelocal
Author: Jonathan Tang
Author-email: jonathan.d.tang@gmail.com
License: MIT License
Platform: Any
Classifier: Development Status :: 4 - Beta
Classifier: Intended Audience :: Developers
Classifier: License :: OSI Approved :: MIT License
Classifier: Programming Language :: Python
